tridge/__init__.py
tridge-0.1.0.dist-info/METADATA
tridge-0.1.0.dist-info/WHEEL
tridge-0.1.0.dist-info/RECORD
